pysnowfall/__init__.py
pysnowfall/helpers.py
pysnowfall/parsers.py
pysnowfall/snowfall.py
pysnowfall/snowfallConfig.py
pysnowfall/snowflake.py
pysnowfall-1.0.0.dist-info/licenses/LICENSE
pysnowfall-1.0.0.dist-info/METADATA
pysnowfall-1.0.0.dist-info/WHEEL
pysnowfall-1.0.0.dist-info/top_level.txt
pysnowfall-1.0.0.dist-info/RECORD
