Metadata-Version: 2.4
Name: pysnowfall
Version: 1.0.0
Summary: A Python Implementation of a Snowflake ID Generator (based on PedroCavaleiro/Avalanche)
Home-page: https://github.com/AshKetshup/Snowfall
Author: AshKetshup
Author-email: dsimoes2000@gmail.com
Classifier: Programming Language :: Python :: 3
Classifier: License :: OSI Approved :: MIT License
Classifier: Operating System :: OS Independent
Requires-Python: >=3.11
License-File: LICENSE
Dynamic: author
Dynamic: author-email
Dynamic: classifier
Dynamic: description
Dynamic: description-content-type
Dynamic: home-page
Dynamic: license-file
Dynamic: requires-python
Dynamic: summary
